oclrfc/__init__.py
oclrfc/_classifier.py
oclrfc/_converter.py
oclrfc/_feature_sets.py
oclrfc/_label_classifier.py
oclrfc/_utils.py
oclrfc-0.4.1.dist-info/LICENSE
oclrfc-0.4.1.dist-info/METADATA
oclrfc-0.4.1.dist-info/WHEEL
oclrfc-0.4.1.dist-info/top_level.txt
oclrfc-0.4.1.dist-info/RECORD
