Metadata-Version: 2.1
Name: oclrfc
Version: 0.4.1
Summary: OpenCL-based Random Forest Classifier
Home-page: https://github.com/haesleinhuepf/oclrfc
Author: haesleinhuepf
Author-email: robert.haase@tu-dresden.de
License: UNKNOWN
Platform: UNKNOWN
Classifier: Programming Language :: Python :: 3
Classifier: License :: OSI Approved :: BSD License
Classifier: Operating System :: OS Independent
Classifier: Intended Audience :: Science/Research
Classifier: Development Status :: 3 - Alpha
Requires-Python: >=3.6
License-File: LICENSE
Requires-Dist: numpy (!=1.19.4)
Requires-Dist: scikit-learn (>=0.24.2)
Requires-Dist: pyclesperanto-prototype (>=0.8.0)
